BASIC_README.txt
CHANGELOG.txt
LICENSE.txt
MANIFEST.in
README.md
setup.py
version.txt
leetcodeDriverPY/__init__.py
leetcodeDriverPY/supportClasses.py
leetcodeDriverPY.egg-info/PKG-INFO
leetcodeDriverPY.egg-info/SOURCES.txt
leetcodeDriverPY.egg-info/dependency_links.txt
leetcodeDriverPY.egg-info/top_level.txt