Metadata-Version: 2.1
Name: leetcodeDriverPY
Version: 1.1.1
Summary: A simple library to help people run Leetcode testcases without the Leetcode online IDE.
Home-page: UNKNOWN
Author: Duve3
Author-email: Duv3tabest@gmail.com
License: MIT
Project-URL: Github, https://github.com/Duve3/leetcodeDriverPY
Project-URL: Issue Tracker, https://github.com/Duve3/leetcodeDriverPY/issues
Keywords: leetcode
Platform: UNKNOWN
Classifier: Development Status :: 5 - Production/Stable
Classifier: Intended Audience :: Education
Classifier: Operating System :: OS Independent
Classifier: License :: OSI Approved :: MIT License
Classifier: Programming Language :: Python :: 3
License-File: LICENSE.txt
